bq_airflow_dag_generator/__init__.py
bq_airflow_dag_generator-0.2.0.dist-info/WHEEL
bq_airflow_dag_generator-0.2.0.dist-info/METADATA
bq_airflow_dag_generator-0.2.0.dist-info/RECORD
