Metadata-Version: 2.1
Name: bq-airflow-dag-generator
Version: 0.2.0
Summary: Generate Airflow DAG from DOT language to execute BigQuery efficiently mainly for AlphaSQL
License: Apache 2.0
Author: Matts966
Author-email: Matts966@users.noreply.github.com
Requires-Python: >=3.6,<4.0
Classifier: License :: Other/Proprietary License
Classifier: Programming Language :: Python :: 3
Classifier: Programming Language :: Python :: 3.6
Classifier: Programming Language :: Python :: 3.7
Classifier: Programming Language :: Python :: 3.8
Classifier: Programming Language :: Python :: 3.9
Requires-Dist: apache-airflow (>=2.0,<3.0)
Requires-Dist: google-cloud-bigquery (>=2.3.1,<3.0.0)
Requires-Dist: networkx (>=2.5,<3.0)
Requires-Dist: pydot (>=1.4.1,<2.0.0)
